napalm_raisecom_di_di
